setup.cfg
setup.py
ExRandom.egg-info/PKG-INFO
ExRandom.egg-info/SOURCES.txt
ExRandom.egg-info/dependency_links.txt
ExRandom.egg-info/requires.txt
ExRandom.egg-info/top_level.txt
ExRandom_api/__init__.py
ExRandom_api/rand.py