Metadata-Version: 2.1
Name: ExRandom
Version: 0.1.0
Requires-Python: >=3.7
Requires-Dist: requests
Requires-Dist: beautifulsoup4
